Workbook

Sheet Dashboard
A1: Harbor Street Bakery — Company Analysis
A2: Generated October 04, 2026
A4: Revenue 2024 | B4: Revenue CAGR | C4: Net Margin | D4: ROE | E4: Current Ratio | F4: Debt / Equity
A5: $1.0M | B5: 11.3% | C5: 9.5% | D5: 27.4% | E5: 2.42x | F5: 0.74x
A7: Financial Health Score
A8: 75.4 | B8: Grade B
A10: Component | B10: Weight | C10: Score
A11: Profitability | B11: 0.25 | C11: 0.4729064
A12: Growth | B12: 0.25 | C12: 0.75044531
A13: Liquidity | B13: 0.2 | C13: 1
A14: Leverage | B14: 0.15 | C14: 0.90285714
A15: Cash Generation | B15: 0.15 | C15: no data
A17: Key Insights
A18: ✔ Revenue grew from $820.0K to $1.0M (11.3% CAGR over 2 years).
A19: ✔ Net margin expanded from 7.4% to 9.5%.
A20: ✔ Gross margin of 60.9% in 2024.
A21: ✔ Return on equity is strong at 27.4%.
A22: ✔ Current ratio of 2.42x covers short-term obligations.
A23: ✔ Debt-to-equity of 0.74x.
A25: Score = weighted blend of net margin, revenue CAGR, current ratio, debt-to-equity and FCF margin. For informational purposes only.

Sheet Financials
A1: Harbor Street Bakery — Financial Statements
A2: Generated October 04, 2026
A4: Line Item | B4: 2022 | C4: 2023 | D4: 2024
A5: Revenue | B5: 820000 | C5: 910000 | D5: 1015000
A6: Cost of Goods Sold | B6: 330000 | C6: 361000 | D6: 397000
A7: Operating Expenses | B7: 380000 | C7: 411000 | D7: 450000
A8: Interest Expense | B8: 14000 | C8: 12500 | D8: 11000
A9: Taxes | B9: 35000 | C9: 47500 | D9: 61000
A10: Net Income | B10: 61000 | C10: 78000 | D10: 96000
A11: Total Assets | C11: 540000 | D11: 610000
A12: Total Liabilities | C12: 240000 | D12: 260000
A13: Shareholder Equity | C13: 300000 | D13: 350000
A14: Current Assets | C14: 200000 | D14: 230000
A15: Current Liabilities | C15: 85000 | D15: 95000
A16: Cash | C16: 150000 | D16: 185000

Sheet Ratios
A1: Harbor Street Bakery — Key Ratios
A2: Generated October 04, 2026 · Live formulas linked to Financials
A4: Ratio | B4: 2022 | C4: 2023 | D4: 2024
A5: Gross Margin | B5: =IFERROR((Financials!$B$5-Financials!$B$6)/Financials!$B$5,"") | C5: =IFERROR((Financials!$C$5-Financials!$C$6)/Financials!$C$5,"") | D5: =IFERROR((Financials!$D$5-Financials!$D$6)/Financials!$D$5,"")
A6: Operating Margin | B6: =IFERROR((Financials!$B$5-Financials!$B$6-Financials!$B$7)/Financials!$B$5,"") | C6: =IFERROR((Financials!$C$5-Financials!$C$6-Financials!$C$7)/Financials!$C$5,"") | D6: =IFERROR((Financials!$D$5-Financials!$D$6-Financials!$D$7)/Financials!$D$5,"")
A7: Net Margin | B7: =IFERROR(Financials!$B$10/Financials!$B$5,"") | C7: =IFERROR(Financials!$C$10/Financials!$C$5,"") | D7: =IFERROR(Financials!$D$10/Financials!$D$5,"")
A8: Revenue Growth (YoY) | C8: =IFERROR((Financials!$C$5-Financials!$B$5)/ABS(Financials!$B$5),"") | D8: =IFERROR((Financials!$D$5-Financials!$C$5)/ABS(Financials!$C$5),"")
A9: Net Income Growth (YoY) | C9: =IFERROR((Financials!$C$10-Financials!$B$10)/ABS(Financials!$B$10),"") | D9: =IFERROR((Financials!$D$10-Financials!$C$10)/ABS(Financials!$C$10),"")
A10: Return on Assets | B10: =IFERROR(Financials!$B$10/Financials!$B$11,"") | C10: =IFERROR(Financials!$C$10/Financials!$C$11,"") | D10: =IFERROR(Financials!$D$10/Financials!$D$11,"")
A11: Return on Equity | B11: =IFERROR(Financials!$B$10/Financials!$B$13,"") | C11: =IFERROR(Financials!$C$10/Financials!$C$13,"") | D11: =IFERROR(Financials!$D$10/Financials!$D$13,"")
A12: Current Ratio | B12: =IFERROR(Financials!$B$14/Financials!$B$15,"") | C12: =IFERROR(Financials!$C$14/Financials!$C$15,"") | D12: =IFERROR(Financials!$D$14/Financials!$D$15,"")
A13: Debt to Equity | B13: =IFERROR(Financials!$B$12/Financials!$B$13,"") | C13: =IFERROR(Financials!$C$12/Financials!$C$13,"") | D13: =IFERROR(Financials!$D$12/Financials!$D$13,"")
A14: Interest Coverage | B14: =IFERROR((Financials!$B$5-Financials!$B$6-Financials!$B$7)/Financials!$B$8,"") | C14: =IFERROR((Financials!$C$5-Financials!$C$6-Financials!$C$7)/Financials!$C$8,"") | D14: =IFERROR((Financials!$D$5-Financials!$D$6-Financials!$D$7)/Financials!$D$8,"")

Sheet Forecast
A1: Harbor Street Bakery — Projection
A2: Generated October 04, 2026
A4: Assumptions (edit the yellow cells)
A5: Annual revenue growth | B5: 0.1125668
A6: Net margin | B6: 0.08489527
A8: Year | B8: Revenue | C8: Net Income | D8: Type
A9: 2022 | B9: 820000 | C9: 61000 | D9: Actual
A10: 2023 | B10: 910000 | C10: 78000 | D10: Actual
A11: 2024 | B11: 1015000 | C11: 96000 | D11: Actual
A12: =A11+1 | B12: =B11*(1+$B$5) | C12: =B12*$B$6 | D12: Forecast
A13: =A12+1 | B13: =B12*(1+$B$5) | C13: =B13*$B$6 | D13: Forecast
A14: =A13+1 | B14: =B13*(1+$B$5) | C14: =B14*$B$6 | D14: Forecast
A16: Projection uses the historical revenue CAGR and the average net margin of the last 3 years. It is an illustration, not investment advice.
