Workbook

Sheet Dashboard
A1: Summit Logistics — Company Analysis
A2: Generated October 04, 2026
A4: Revenue 2024 | B4: Revenue CAGR | C4: Net Margin | D4: ROE | E4: Current Ratio | F4: Debt / Equity
A5: $18.7M | B5: 0.3% | C5: -1.4% | D5: -4.2% | E5: 0.74x | F5: 3.13x
A7: Financial Health Score
A8: 7.9 | B8: Grade F
A10: Component | B10: Weight | C10: Score
A11: Profitability | B11: 0.25 | C11: 0
A12: Growth | B12: 0.25 | C12: 0.017945429
A13: Liquidity | B13: 0.2 | C13: 0.37096774
A14: Leverage | B14: 0.15 | C14: 0
A15: Cash Generation | B15: 0.15 | C15: 0
A17: Key Insights
A18: ✔ Revenue grew from $18.5M to $18.7M (0.3% CAGR over 4 years).
A19: ✔ Net margin contracted from 2.1% to -1.4%.
A20: ✔ Gross margin of 21.0% in 2024.
A21: ✔ Return on equity is weak at -4.2%.
A23: Watch-outs
A24: ⚠ Revenue fell 3.1% in 2024.
A25: ⚠ The company lost money in 2024 (net margin -1.4%).
A26: ⚠ Current ratio of 0.74x — short-term liabilities exceed current assets.
A27: ⚠ High leverage: debt-to-equity of 3.13x.
A28: ⚠ Interest coverage is thin at 0.7x operating income.
A29: ⚠ Negative free cash flow of -$810.0K in 2024.
A31: Score = weighted blend of net margin, revenue CAGR, current ratio, debt-to-equity and FCF margin. For informational purposes only.

Sheet Financials
A1: Summit Logistics — Financial Statements
A2: Generated October 04, 2026
A4: Line Item | B4: 2020 | C4: 2021 | D4: 2022 | E4: 2023 | F4: 2024
A5: Revenue | B5: 18500000 | C5: 19200000 | D5: 19900000 | E5: 19300000 | F5: 18700000
A6: Cost of Goods Sold | B6: 14060000 | C6: 14784000 | D6: 15522000 | E6: 15247000 | F6: 14773000
A7: Operating Expenses | B7: 3330000 | C7: 3456000 | D7: 3582000 | E7: 3474000 | F7: 3366000
A8: Interest Expense | B8: 610000 | C8: 650000 | D8: 720000 | E8: 780000 | F8: 820000
A9: Taxes | B9: 120000 | C9: 90000 | D9: 20000 | E9: 0 | F9: 0
A10: Net Income | B10: 380000 | C10: 220000 | D10: 56000 | E10: -201000 | F10: -259000
A11: Total Assets | B11: 22000000 | C11: 23100000 | D11: 24400000 | E11: 24900000 | F11: 25200000
A12: Total Liabilities | B12: 15400000 | C12: 16500000 | D12: 17800000 | E12: 18500000 | F12: 19100000
A13: Shareholder Equity | B13: 6600000 | C13: 6600000 | D13: 6600000 | E13: 6400000 | F13: 6100000
A14: Current Assets | B14: 5200000 | C14: 5100000 | D14: 5000000 | E14: 4800000 | F14: 4600000
A15: Current Liabilities | B15: 4900000 | C15: 5300000 | D15: 5700000 | E15: 6000000 | F15: 6200000
A16: Cash | B16: 900000 | C16: 700000 | D16: 520000 | E16: 410000 | F16: 350000
... A18: Capital Expenditures | B18: 1900000 | C18: 2100000 | D18: 2300000 | E18: 1800000 | F18: 1500000

Sheet Ratios
A1: Summit Logistics — Key Ratios
A2: Generated October 04, 2026 · Live formulas linked to Financials
A4: Ratio | B4: 2020 | C4: 2021 | D4: 2022 | E4: 2023 | F4: 2024
A5: Gross Margin | B5: =IFERROR((Financials!$B$5-Financials!$B$6)/Financials!$B$5,"") | C5: =IFERROR((Financials!$C$5-Financials!$C$6)/Financials!$C$5,"") | D5: =IFERROR((Financials!$D$5-Financials!$D$6)/Financials!$D$5,"") | E5: =IFERROR((Financials!$E$5-Financials!$E$6)/Financials!$E$5,"") | F5: =IFERROR((Financials!$F$5-Financials!$F$6)/Financials!$F$5,"")
A6: Operating Margin | B6: =IFERROR((Financials!$B$5-Financials!$B$6-Financials!$B$7)/Financials!$B$5,"") | C6: =IFERROR((Financials!$C$5-Financials!$C$6-Financials!$C$7)/Financials!$C$5,"") | D6: =IFERROR((Financials!$D$5-Financials!$D$6-Financials!$D$7)/Financials!$D$5,"") | E6: =IFERROR((Financials!$E$5-Financials!$E$6-Financials!$E$7)/Financials!$E$5,"") | F6: =IFERROR((Financials!$F$5-Financials!$F$6-Financials!$F$7)/Financials!$F$5,"")
A7: Net Margin | B7: =IFERROR(Financials!$B$10/Financials!$B$5,"") | C7: =IFERROR(Financials!$C$10/Financials!$C$5,"") | D7: =IFERROR(Financials!$D$10/Financials!$D$5,"") | E7: =IFERROR(Financials!$E$10/Financials!$E$5,"") | F7: =IFERROR(Financials!$F$10/Financials!$F$5,"")
A8: Revenue Growth (YoY) | C8: =IFERROR((Financials!$C$5-Financials!$B$5)/ABS(Financials!$B$5),"") | D8: =IFERROR((Financials!$D$5-Financials!$C$5)/ABS(Financials!$C$5),"") | E8: =IFERROR((Financials!$E$5-Financials!$D$5)/ABS(Financials!$D$5),"") | F8: =IFERROR((Financials!$F$5-Financials!$E$5)/ABS(Financials!$E$5),"")
A9: Net Income Growth (YoY) | C9: =IFERROR((Financials!$C$10-Financials!$B$10)/ABS(Financials!$B$10),"") | D9: =IFERROR((Financials!$D$10-Financials!$C$10)/ABS(Financials!$C$10),"") | E9: =IFERROR((Financials!$E$10-Financials!$D$10)/ABS(Financials!$D$10),"") | F9: =IFERROR((Financials!$F$10-Financials!$E$10)/ABS(Financials!$E$10),"")
A10: Return on Assets | B10: =IFERROR(Financials!$B$10/Financials!$B$11,"") | C10: =IFERROR(Financials!$C$10/Financials!$C$11,"") | D10: =IFERROR(Financials!$D$10/Financials!$D$11,"") | E10: =IFERROR(Financials!$E$10/Financials!$E$11,"") | F10: =IFERROR(Financials!$F$10/Financials!$F$11,"")
A11: Return on Equity | B11: =IFERROR(Financials!$B$10/Financials!$B$13,"") | C11: =IFERROR(Financials!$C$10/Financials!$C$13,"") | D11: =IFERROR(Financials!$D$10/Financials!$D$13,"") | E11: =IFERROR(Financials!$E$10/Financials!$E$13,"") | F11: =IFERROR(Financials!$F$10/Financials!$F$13,"")
A12: Current Ratio | B12: =IFERROR(Financials!$B$14/Financials!$B$15,"") | C12: =IFERROR(Financials!$C$14/Financials!$C$15,"") | D12: =IFERROR(Financials!$D$14/Financials!$D$15,"") | E12: =IFERROR(Financials!$E$14/Financials!$E$15,"") | F12: =IFERROR(Financials!$F$14/Financials!$F$15,"")
A13: Debt to Equity | B13: =IFERROR(Financials!$B$12/Financials!$B$13,"") | C13: =IFERROR(Financials!$C$12/Financials!$C$13,"") | D13: =IFERROR(Financials!$D$12/Financials!$D$13,"") | E13: =IFERROR(Financials!$E$12/Financials!$E$13,"") | F13: =IFERROR(Financials!$F$12/Financials!$F$13,"")
A14: Interest Coverage | B14: =IFERROR((Financials!$B$5-Financials!$B$6-Financials!$B$7)/Financials!$B$8,"") | C14: =IFERROR((Financials!$C$5-Financials!$C$6-Financials!$C$7)/Financials!$C$8,"") | D14: =IFERROR((Financials!$D$5-Financials!$D$6-Financials!$D$7)/Financials!$D$8,"") | E14: =IFERROR((Financials!$E$5-Financials!$E$6-Financials!$E$7)/Financials!$E$8,"") | F14: =IFERROR((Financials!$F$5-Financials!$F$6-Financials!$F$7)/Financials!$F$8,"")
A15: Free Cash Flow | B15: =IFERROR(Financials!$B$17-Financials!$B$18,"") | C15: =IFERROR(Financials!$C$17-Financials!$C$18,"") | D15: =IFERROR(Financials!$D$17-Financials!$D$18,"") | E15: =IFERROR(Financials!$E$17-Financials!$E$18,"") | F15: =IFERROR(Financials!$F$17-Financials!$F$18,"")
A16: FCF Margin | B16: =IFERROR((Financials!$B$17-Financials!$B$18)/Financials!$B$5,"") | C16: =IFERROR((Financials!$C$17-Financials!$C$18)/Financials!$C$5,"") | D16: =IFERROR((Financials!$D$17-Financials!$D$18)/Financials!$D$5,"") | E16: =IFERROR((Financials!$E$17-Financials!$E$18)/Financials!$E$5,"") | F16: =IFERROR((Financials!$F$17-Financials!$F$18)/Financials!$F$5,"")

Sheet Forecast
A1: Summit Logistics — Projection
A2: Generated October 04, 2026
A4: Assumptions (edit the yellow cells)
A5: Annual revenue growth | B5: 0.0026918144
A6: Net margin | B6: -0.0071502349
A8: Year | B8: Revenue | C8: Net Income | D8: Type
A9: 2020 | B9: 18500000 | C9: 380000 | D9: Actual
A10: 2021 | B10: 19200000 | C10: 220000 | D10: Actual
A11: 2022 | B11: 19900000 | C11: 56000 | D11: Actual
A12: 2023 | B12: 19300000 | C12: -201000 | D12: Actual
A13: 2024 | B13: 18700000 | C13: -259000 | D13: Actual
A14: =A13+1 | B14: =B13*(1+$B$5) | C14: =B14*$B$6 | D14: Forecast
A15: =A14+1 | B15: =B14*(1+$B$5) | C15: =B15*$B$6 | D15: Forecast
A16: =A15+1 | B16: =B15*(1+$B$5) | C16: =B16*$B$6 | D16: Forecast
A18: Projection uses the historical revenue CAGR and the average net margin of the last 3 years. It is an illustration, not investment advice.
